[
    {
        "Question": "Which of theses languages were named after a mathematician",
        "options": [
            {
                "content": "Lua",
                "key": "A",
                "correct": false
            },
            {
                "content": "Haskell",
                "key": "B",
                "correct": true
            },
            {
                "content": "Cobol",
                "key": "C",
                "correct": false
            },
            {
                "content": "Ada",
                "key": "D",
                "correct": true
            }
        ]
    }
]
